Metadata-Version: 1.1
Name: mysimplesplit
Version: 0.0.1
Summary: A very basic splitter
Home-page: UNKNOWN
Author: Yaryk Dyhanov
Author-email: duhanov2003@gmail.com
License: MIT
Keywords: split
Platform: UNKNOWN
Classifier: Development Status :: 5 - Production/Stable
Classifier: Intended Audience :: Education
Classifier: License :: OSI Approved :: MIT License
Classifier: Programming Language :: Python :: 3
